{"v":5,"entries":{"get-started--overview":{"id":"get-started--overview","title":"Get Started","name":"Overview","importPath":"./src/stories/GetStarted.mdx","storiesImports":[],"type":"docs","tags":["dev","test","unattached-mdx"]},"components-badge--overview":{"id":"components-badge--overview","title":"Components/Badge","name":"Overview","importPath":"./src/components/Badge/Badge.stories.tsx","type":"docs","tags":["dev","test","autodocs"],"storiesImports":[]},"components-badge--primary":{"type":"story","id":"components-badge--primary","name":"Primary","title":"Components/Badge","importPath":"./src/components/Badge/Badge.stories.tsx","componentPath":"./src/components/Badge/index.ts","tags":["dev","test","autodocs"]},"components-button--overview":{"id":"components-button--overview","title":"Components/Button","name":"Overview","importPath":"./src/components/Button/Button.stories.tsx","type":"docs","tags":["dev","test"],"storiesImports":[]},"components-button--primary":{"type":"story","id":"components-button--primary","name":"Primary","title":"Components/Button","importPath":"./src/components/Button/Button.stories.tsx","componentPath":"./src/components/Button/index.ts","tags":["dev","test"]},"components-button--primary-landing":{"type":"story","id":"components-button--primary-landing","name":"Primary Landing","title":"Components/Button","importPath":"./src/components/Button/Button.stories.tsx","componentPath":"./src/components/Button/index.ts","tags":["dev","test","autodocs"]},"components-button--secondary-landing":{"type":"story","id":"components-button--secondary-landing","name":"Secondary Landing","title":"Components/Button","importPath":"./src/components/Button/Button.stories.tsx","componentPath":"./src/components/Button/index.ts","tags":["dev","test","autodocs"]},"components-calendar--overview":{"id":"components-calendar--overview","title":"Components/Calendar","name":"Overview","importPath":"./src/components/Calendar/Calendar.stories.tsx","type":"docs","tags":["dev","test","autodocs"],"storiesImports":[]},"components-calendar--primary":{"type":"story","id":"components-calendar--primary","name":"Primary","title":"Components/Calendar","importPath":"./src/components/Calendar/Calendar.stories.tsx","componentPath":"./src/components/Calendar/index.ts","tags":["dev","test","autodocs"]},"components-calendar--range":{"type":"story","id":"components-calendar--range","name":"Range","title":"Components/Calendar","importPath":"./src/components/Calendar/Calendar.stories.tsx","componentPath":"./src/components/Calendar/index.ts","tags":["dev","test","autodocs"]},"components-calendar--multiple":{"type":"story","id":"components-calendar--multiple","name":"Multiple","title":"Components/Calendar","importPath":"./src/components/Calendar/Calendar.stories.tsx","componentPath":"./src/components/Calendar/index.ts","tags":["dev","test","autodocs"]},"components-cell--overview":{"id":"components-cell--overview","title":"Components/Cell","name":"Overview","importPath":"./src/components/Cell/Cell.stories.tsx","type":"docs","tags":["dev","test","autodocs"],"storiesImports":[]},"components-cell--default":{"type":"story","id":"components-cell--default","name":"Default","title":"Components/Cell","importPath":"./src/components/Cell/Cell.stories.tsx","componentPath":"./src/components/Cell/index.ts","tags":["dev","test","autodocs"]},"components-checkbox--overview":{"id":"components-checkbox--overview","title":"Components/Checkbox","name":"Overview","importPath":"./src/components/Checkbox/Checkbox.stories.tsx","type":"docs","tags":["dev","test"],"storiesImports":[]},"components-checkbox--basic":{"type":"story","id":"components-checkbox--basic","name":"Basic","title":"Components/Checkbox","importPath":"./src/components/Checkbox/Checkbox.stories.tsx","componentPath":"./src/components/Checkbox/index.ts","tags":["dev","test"]},"components-checkbox--no-label":{"type":"story","id":"components-checkbox--no-label","name":"No Label","title":"Components/Checkbox","importPath":"./src/components/Checkbox/Checkbox.stories.tsx","componentPath":"./src/components/Checkbox/index.ts","tags":["dev","test","autodocs"]},"components-checkbox--checked":{"type":"story","id":"components-checkbox--checked","name":"Checked","title":"Components/Checkbox","importPath":"./src/components/Checkbox/Checkbox.stories.tsx","componentPath":"./src/components/Checkbox/index.ts","tags":["dev","test","autodocs"]},"components-checkbox--invalid":{"type":"story","id":"components-checkbox--invalid","name":"Invalid","title":"Components/Checkbox","importPath":"./src/components/Checkbox/Checkbox.stories.tsx","componentPath":"./src/components/Checkbox/index.ts","tags":["dev","test","autodocs"]},"components-checkbox--small":{"type":"story","id":"components-checkbox--small","name":"Small","title":"Components/Checkbox","importPath":"./src/components/Checkbox/Checkbox.stories.tsx","componentPath":"./src/components/Checkbox/index.ts","tags":["dev","test","autodocs"]},"components-checkbox--medium":{"type":"story","id":"components-checkbox--medium","name":"Medium","title":"Components/Checkbox","importPath":"./src/components/Checkbox/Checkbox.stories.tsx","componentPath":"./src/components/Checkbox/index.ts","tags":["dev","test","autodocs"]},"components-checkbox--large":{"type":"story","id":"components-checkbox--large","name":"Large","title":"Components/Checkbox","importPath":"./src/components/Checkbox/Checkbox.stories.tsx","componentPath":"./src/components/Checkbox/index.ts","tags":["dev","test","autodocs"]},"components-checkbox--disabled":{"type":"story","id":"components-checkbox--disabled","name":"Disabled","title":"Components/Checkbox","importPath":"./src/components/Checkbox/Checkbox.stories.tsx","componentPath":"./src/components/Checkbox/index.ts","tags":["dev","test","autodocs"]},"components-checkbox--disabled-checked":{"type":"story","id":"components-checkbox--disabled-checked","name":"Disabled Checked","title":"Components/Checkbox","importPath":"./src/components/Checkbox/Checkbox.stories.tsx","componentPath":"./src/components/Checkbox/index.ts","tags":["dev","test","autodocs"]},"components-checkbox--tristate":{"type":"story","id":"components-checkbox--tristate","name":"Tristate","title":"Components/Checkbox","importPath":"./src/components/Checkbox/Checkbox.stories.tsx","componentPath":"./src/components/Checkbox/index.ts","tags":["dev","test","autodocs"]},"components-checkbox--tristate-checked":{"type":"story","id":"components-checkbox--tristate-checked","name":"Tristate Checked","title":"Components/Checkbox","importPath":"./src/components/Checkbox/Checkbox.stories.tsx","componentPath":"./src/components/Checkbox/index.ts","tags":["dev","test","autodocs"]},"components-checkboxgroup--overview":{"id":"components-checkboxgroup--overview","title":"Components/CheckboxGroup","name":"Overview","importPath":"./src/components/CheckboxGroup/CheckboxGroup.stories.tsx","type":"docs","tags":["dev","test"],"storiesImports":[]},"components-checkboxgroup--single":{"type":"story","id":"components-checkboxgroup--single","name":"Single","title":"Components/CheckboxGroup","importPath":"./src/components/CheckboxGroup/CheckboxGroup.stories.tsx","componentPath":"./src/components/CheckboxGroup/index.ts","tags":["dev","test"]},"components-checkboxgroup--no-label":{"type":"story","id":"components-checkboxgroup--no-label","name":"No Label","title":"Components/CheckboxGroup","importPath":"./src/components/CheckboxGroup/CheckboxGroup.stories.tsx","componentPath":"./src/components/CheckboxGroup/index.ts","tags":["dev","test","autodocs"]},"components-checkboxgroup--invalid":{"type":"story","id":"components-checkboxgroup--invalid","name":"Invalid","title":"Components/CheckboxGroup","importPath":"./src/components/CheckboxGroup/CheckboxGroup.stories.tsx","componentPath":"./src/components/CheckboxGroup/index.ts","tags":["dev","test","autodocs"]},"components-checkboxgroup--size":{"type":"story","id":"components-checkboxgroup--size","name":"Size","title":"Components/CheckboxGroup","importPath":"./src/components/CheckboxGroup/CheckboxGroup.stories.tsx","componentPath":"./src/components/CheckboxGroup/index.ts","tags":["dev","test","autodocs"]},"components-checkboxgroup--disabled":{"type":"story","id":"components-checkboxgroup--disabled","name":"Disabled","title":"Components/CheckboxGroup","importPath":"./src/components/CheckboxGroup/CheckboxGroup.stories.tsx","componentPath":"./src/components/CheckboxGroup/index.ts","tags":["dev","test","autodocs"]},"components-checkboxgroup--single-tristate":{"type":"story","id":"components-checkboxgroup--single-tristate","name":"Single Tristate","title":"Components/CheckboxGroup","importPath":"./src/components/CheckboxGroup/CheckboxGroup.stories.tsx","componentPath":"./src/components/CheckboxGroup/index.ts","tags":["dev","test","autodocs"]},"components-checkboxgroup--multiple":{"type":"story","id":"components-checkboxgroup--multiple","name":"Multiple","title":"Components/CheckboxGroup","importPath":"./src/components/CheckboxGroup/CheckboxGroup.stories.tsx","componentPath":"./src/components/CheckboxGroup/index.ts","tags":["dev","test","autodocs"]},"components-checkboxgroup--multiple-tristate":{"type":"story","id":"components-checkboxgroup--multiple-tristate","name":"Multiple Tristate","title":"Components/CheckboxGroup","importPath":"./src/components/CheckboxGroup/CheckboxGroup.stories.tsx","componentPath":"./src/components/CheckboxGroup/index.ts","tags":["dev","test","autodocs"]},"components-clipboard--overview":{"id":"components-clipboard--overview","title":"Components/Clipboard","name":"Overview","importPath":"./src/components/Clipboard/Clipboard.stories.tsx","type":"docs","tags":["dev","test","autodocs"],"storiesImports":[]},"components-clipboard--primary":{"type":"story","id":"components-clipboard--primary","name":"Primary","title":"Components/Clipboard","importPath":"./src/components/Clipboard/Clipboard.stories.tsx","componentPath":"./src/components/Clipboard/index.ts","tags":["dev","test","autodocs"]},"components-collapse--overview":{"id":"components-collapse--overview","title":"Components/Collapse","name":"Overview","importPath":"./src/components/Collapse/Collapse.stories.tsx","type":"docs","tags":["dev","test","autodocs"],"storiesImports":[]},"components-collapse--primary":{"type":"story","id":"components-collapse--primary","name":"Primary","title":"Components/Collapse","importPath":"./src/components/Collapse/Collapse.stories.tsx","componentPath":"./src/components/Collapse/index.ts","tags":["dev","test","autodocs"]},"components-confirmpopup--overview":{"id":"components-confirmpopup--overview","title":"Components/ConfirmPopup","name":"Overview","importPath":"./src/components/ConfirmPopup/ConfirmPopup.stories.tsx","type":"docs","tags":["dev","test","autodocs"],"storiesImports":[]},"components-confirmpopup--primary":{"type":"story","id":"components-confirmpopup--primary","name":"Primary","title":"Components/ConfirmPopup","importPath":"./src/components/ConfirmPopup/ConfirmPopup.stories.tsx","componentPath":"./src/components/ConfirmPopup/index.ts","tags":["dev","test","autodocs"]},"components-copy--overview":{"id":"components-copy--overview","title":"Components/Copy","name":"Overview","importPath":"./src/components/Copy/Copy.stories.tsx","type":"docs","tags":["dev","test","autodocs"],"storiesImports":[]},"components-copy--primary":{"type":"story","id":"components-copy--primary","name":"Primary","title":"Components/Copy","importPath":"./src/components/Copy/Copy.stories.tsx","componentPath":"./src/components/Copy/index.ts","tags":["dev","test","autodocs"]},"components-drawer--overview":{"id":"components-drawer--overview","title":"Components/Drawer","name":"Overview","importPath":"./src/components/Drawer/Drawer.stories.tsx","type":"docs","tags":["dev","test","autodocs"],"storiesImports":[]},"components-drawer--primary":{"type":"story","id":"components-drawer--primary","name":"Primary","title":"Components/Drawer","importPath":"./src/components/Drawer/Drawer.stories.tsx","componentPath":"./src/components/Drawer/index.ts","tags":["dev","test","autodocs"]},"components-dropdown--overview":{"id":"components-dropdown--overview","title":"Components/Dropdown","name":"Overview","importPath":"./src/components/Dropdown/Dropdown.stories.tsx","type":"docs","tags":["dev","test","autodocs"],"storiesImports":[]},"components-dropdown--primary":{"type":"story","id":"components-dropdown--primary","name":"Primary","title":"Components/Dropdown","importPath":"./src/components/Dropdown/Dropdown.stories.tsx","componentPath":"./src/components/Dropdown/index.ts","tags":["dev","test","autodocs"]},"components-icons--overview":{"id":"components-icons--overview","title":"Components/Icons","name":"Overview","importPath":"./src/components/Icons/Icons.stories.tsx","type":"docs","tags":["dev","test","autodocs"],"storiesImports":[]},"components-icons--primary-icons":{"type":"story","id":"components-icons--primary-icons","name":"Primary Icons","title":"Components/Icons","importPath":"./src/components/Icons/Icons.stories.tsx","componentPath":"./src/components/Icons/index.ts","tags":["dev","test","autodocs"]},"components-icons--logo":{"type":"story","id":"components-icons--logo","name":"Logo","title":"Components/Icons","importPath":"./src/components/Icons/Icons.stories.tsx","componentPath":"./src/components/Icons/index.ts","tags":["dev","test","autodocs"]},"components-icons--illustrations":{"type":"story","id":"components-icons--illustrations","name":"Illustrations","title":"Components/Icons","importPath":"./src/components/Icons/Icons.stories.tsx","componentPath":"./src/components/Icons/index.ts","tags":["dev","test","autodocs"]},"components-icons--old-icons":{"type":"story","id":"components-icons--old-icons","name":"Old Icons (Deprecated)","title":"Components/Icons","importPath":"./src/components/Icons/Icons.stories.tsx","componentPath":"./src/components/Icons/index.ts","tags":["dev","test","autodocs"]},"components-input--overview":{"id":"components-input--overview","title":"Components/Input","name":"Overview","importPath":"./src/components/Input/Input.stories.tsx","type":"docs","tags":["dev","test"],"storiesImports":[]},"components-input--normal":{"type":"story","id":"components-input--normal","name":"Normal","title":"Components/Input","importPath":"./src/components/Input/Input.stories.tsx","componentPath":"./src/components/Input/index.ts","tags":["dev","test"]},"components-input--number":{"type":"story","id":"components-input--number","name":"Number","title":"Components/Input","importPath":"./src/components/Input/Input.stories.tsx","componentPath":"./src/components/Input/index.ts","tags":["dev","test","autodocs"]},"components-input--password":{"type":"story","id":"components-input--password","name":"Password","title":"Components/Input","importPath":"./src/components/Input/Input.stories.tsx","componentPath":"./src/components/Input/index.ts","tags":["dev","test","autodocs"]},"components-input--auto-complete":{"type":"story","id":"components-input--auto-complete","name":"Auto Complete","title":"Components/Input","importPath":"./src/components/Input/Input.stories.tsx","componentPath":"./src/components/Input/index.ts","tags":["dev","test","autodocs"]},"components-input--mask":{"type":"story","id":"components-input--mask","name":"Mask","title":"Components/Input","importPath":"./src/components/Input/Input.stories.tsx","componentPath":"./src/components/Input/index.ts","tags":["dev","test","autodocs"]},"components-input--otp-code":{"type":"story","id":"components-input--otp-code","name":"Otp Code","title":"Components/Input","importPath":"./src/components/Input/Input.stories.tsx","componentPath":"./src/components/Input/index.ts","tags":["dev","test","autodocs"]},"components-input--text-area":{"type":"story","id":"components-input--text-area","name":"Text Area","title":"Components/Input","importPath":"./src/components/Input/Input.stories.tsx","componentPath":"./src/components/Input/index.ts","tags":["dev","test","autodocs"]},"components-inputamount--overview":{"id":"components-inputamount--overview","title":"Components/InputAmount","name":"Overview","importPath":"./src/components/InputAmount/InputAmount.stories.tsx","type":"docs","tags":["dev","test","autodocs"],"storiesImports":[]},"components-inputamount--primary":{"type":"story","id":"components-inputamount--primary","name":"Primary","title":"Components/InputAmount","importPath":"./src/components/InputAmount/InputAmount.stories.tsx","componentPath":"./src/components/InputAmount/index.ts","tags":["dev","test","autodocs"]},"components-loading--overview":{"id":"components-loading--overview","title":"Components/Loading","name":"Overview","importPath":"./src/components/Loading/Loading.stories.tsx","type":"docs","tags":["dev","test"],"storiesImports":[]},"components-loading--pure":{"type":"story","id":"components-loading--pure","name":"Pure","title":"Components/Loading","importPath":"./src/components/Loading/Loading.stories.tsx","componentPath":"./src/components/Loading/index.ts","tags":["dev","test"]},"components-loading--pattern":{"type":"story","id":"components-loading--pattern","name":"Pattern","title":"Components/Loading","importPath":"./src/components/Loading/Loading.stories.tsx","componentPath":"./src/components/Loading/index.ts","tags":["dev","test","autodocs"]},"components-menu--overview":{"id":"components-menu--overview","title":"Components/Menu","name":"Overview","importPath":"./src/components/Menu/Menu.stories.tsx","type":"docs","tags":["dev","test","autodocs"],"storiesImports":[]},"components-menu--primary":{"type":"story","id":"components-menu--primary","name":"Primary","title":"Components/Menu","importPath":"./src/components/Menu/Menu.stories.tsx","componentPath":"./src/components/Menu/index.ts","tags":["dev","test","autodocs"]},"components-message--overview":{"id":"components-message--overview","title":"Components/Message","name":"Overview","importPath":"./src/components/Message/Message.stories.tsx","type":"docs","tags":["dev","test"],"storiesImports":[]},"components-message--success":{"type":"story","id":"components-message--success","name":"Success","title":"Components/Message","importPath":"./src/components/Message/Message.stories.tsx","componentPath":"./src/components/Message/index.ts","tags":["dev","test"]},"components-message--warn":{"type":"story","id":"components-message--warn","name":"Warn","title":"Components/Message","importPath":"./src/components/Message/Message.stories.tsx","componentPath":"./src/components/Message/index.ts","tags":["dev","test","autodocs"]},"components-message--error":{"type":"story","id":"components-message--error","name":"Error","title":"Components/Message","importPath":"./src/components/Message/Message.stories.tsx","componentPath":"./src/components/Message/index.ts","tags":["dev","test","autodocs"]},"components-message--info":{"type":"story","id":"components-message--info","name":"Info","title":"Components/Message","importPath":"./src/components/Message/Message.stories.tsx","componentPath":"./src/components/Message/index.ts","tags":["dev","test","autodocs"]},"components-modal--overview":{"id":"components-modal--overview","title":"Components/Modal","name":"Overview","importPath":"./src/components/Modal/Modal.stories.tsx","type":"docs","tags":["dev","test"],"storiesImports":[]},"components-modal--normal":{"type":"story","id":"components-modal--normal","name":"Normal","title":"Components/Modal","importPath":"./src/components/Modal/Modal.stories.tsx","componentPath":"./src/components/Modal/index.ts","tags":["dev","test"]},"components-modal--confirm":{"type":"story","id":"components-modal--confirm","name":"Confirm","title":"Components/Modal","importPath":"./src/components/Modal/Modal.stories.tsx","componentPath":"./src/components/Modal/index.ts","tags":["dev","test","autodocs"]},"components-notification--overview":{"id":"components-notification--overview","title":"Components/Notification","name":"Overview","importPath":"./src/components/Notification/Notification.stories.tsx","type":"docs","tags":["dev","test","autodocs"],"storiesImports":[]},"components-notification--primary":{"type":"story","id":"components-notification--primary","name":"Primary","title":"Components/Notification","importPath":"./src/components/Notification/Notification.stories.tsx","componentPath":"./src/components/Notification/index.ts","tags":["dev","test","autodocs"]},"components-popup--overview":{"id":"components-popup--overview","title":"Components/Popup","name":"Overview","importPath":"./src/components/Popup/Popup.stories.tsx","type":"docs","tags":["dev","test","autodocs"],"storiesImports":[]},"components-popup--primary":{"type":"story","id":"components-popup--primary","name":"Primary","title":"Components/Popup","importPath":"./src/components/Popup/Popup.stories.tsx","componentPath":"./src/components/Popup/index.ts","tags":["dev","test","autodocs"]},"components-progress--overview":{"id":"components-progress--overview","title":"Components/Progress","name":"Overview","importPath":"./src/components/Progress/Progress.stories.tsx","type":"docs","tags":["dev","test","autodocs"],"storiesImports":[]},"components-progress--ring":{"type":"story","id":"components-progress--ring","name":"Ring","title":"Components/Progress","importPath":"./src/components/Progress/Progress.stories.tsx","componentPath":"./src/components/Progress/index.ts","tags":["dev","test","autodocs"]},"components-progress--bar":{"type":"story","id":"components-progress--bar","name":"Bar","title":"Components/Progress","importPath":"./src/components/Progress/Progress.stories.tsx","componentPath":"./src/components/Progress/index.ts","tags":["dev","test","autodocs"]},"components-radio--overview":{"id":"components-radio--overview","title":"Components/Radio","name":"Overview","importPath":"./src/components/Radio/Radio.stories.tsx","type":"docs","tags":["dev","test","autodocs"],"storiesImports":[]},"components-radio--default":{"type":"story","id":"components-radio--default","name":"Default","title":"Components/Radio","importPath":"./src/components/Radio/Radio.stories.tsx","componentPath":"./src/components/Radio/index.ts","tags":["dev","test","autodocs"]},"components-radio--disabled":{"type":"story","id":"components-radio--disabled","name":"Disabled","title":"Components/Radio","importPath":"./src/components/Radio/Radio.stories.tsx","componentPath":"./src/components/Radio/index.ts","tags":["dev","test","autodocs"]},"components-radio--invalid":{"type":"story","id":"components-radio--invalid","name":"Invalid","title":"Components/Radio","importPath":"./src/components/Radio/Radio.stories.tsx","componentPath":"./src/components/Radio/index.ts","tags":["dev","test","autodocs"]},"components-radio--size":{"type":"story","id":"components-radio--size","name":"Size","title":"Components/Radio","importPath":"./src/components/Radio/Radio.stories.tsx","componentPath":"./src/components/Radio/index.ts","tags":["dev","test","autodocs"]},"components-radio--radio-group":{"type":"story","id":"components-radio--radio-group","name":"Radio Group","title":"Components/Radio","importPath":"./src/components/Radio/Radio.stories.tsx","componentPath":"./src/components/Radio/index.ts","tags":["dev","test","autodocs"]},"components-radiogroup--overview":{"id":"components-radiogroup--overview","title":"Components/RadioGroup","name":"Overview","importPath":"./src/components/RadioGroup/RadioGroup.stories.tsx","type":"docs","tags":["dev","test","autodocs"],"storiesImports":[]},"components-radiogroup--group-size-small":{"type":"story","id":"components-radiogroup--group-size-small","name":"Group Size Small","title":"Components/RadioGroup","importPath":"./src/components/RadioGroup/RadioGroup.stories.tsx","componentPath":"./src/components/RadioGroup/index.ts","tags":["dev","test","autodocs"]},"components-radiogroup--group-disabled":{"type":"story","id":"components-radiogroup--group-disabled","name":"Group Disabled","title":"Components/RadioGroup","importPath":"./src/components/RadioGroup/RadioGroup.stories.tsx","componentPath":"./src/components/RadioGroup/index.ts","tags":["dev","test","autodocs"]},"components-radiogroup--group-size-medium":{"type":"story","id":"components-radiogroup--group-size-medium","name":"Group Size Medium","title":"Components/RadioGroup","importPath":"./src/components/RadioGroup/RadioGroup.stories.tsx","componentPath":"./src/components/RadioGroup/index.ts","tags":["dev","test","autodocs"]},"components-radiogroup--group-size-large":{"type":"story","id":"components-radiogroup--group-size-large","name":"Group Size Large","title":"Components/RadioGroup","importPath":"./src/components/RadioGroup/RadioGroup.stories.tsx","componentPath":"./src/components/RadioGroup/index.ts","tags":["dev","test","autodocs"]},"components-radiogroup--group-variant-card":{"type":"story","id":"components-radiogroup--group-variant-card","name":"Group Variant Card","title":"Components/RadioGroup","importPath":"./src/components/RadioGroup/RadioGroup.stories.tsx","componentPath":"./src/components/RadioGroup/index.ts","tags":["dev","test","autodocs"]},"components-radiogroup--payment-method":{"type":"story","id":"components-radiogroup--payment-method","name":"Payment Method","title":"Components/RadioGroup","importPath":"./src/components/RadioGroup/RadioGroup.stories.tsx","componentPath":"./src/components/RadioGroup/index.ts","tags":["dev","test","autodocs"]},"components-select--overview":{"id":"components-select--overview","title":"Components/Select","name":"Overview","importPath":"./src/components/Select/Select.stories.tsx","type":"docs","tags":["dev","test"],"storiesImports":[]},"components-select--test":{"type":"story","id":"components-select--test","name":"Test","title":"Components/Select","importPath":"./src/components/Select/Select.stories.tsx","componentPath":"./src/components/Select/index.ts","tags":["dev","test"]},"components-select--single":{"type":"story","id":"components-select--single","name":"Single","title":"Components/Select","importPath":"./src/components/Select/Select.stories.tsx","componentPath":"./src/components/Select/index.ts","tags":["dev","test"]},"components-select--multiple":{"type":"story","id":"components-select--multiple","name":"Multiple","title":"Components/Select","importPath":"./src/components/Select/Select.stories.tsx","componentPath":"./src/components/Select/index.ts","tags":["dev","test","autodocs"]},"components-select--custom-dropdown":{"type":"story","id":"components-select--custom-dropdown","name":"Custom Dropdown","title":"Components/Select","importPath":"./src/components/Select/Select.stories.tsx","componentPath":"./src/components/Select/index.ts","tags":["dev","test","autodocs"]},"components-select--custom-item-template":{"type":"story","id":"components-select--custom-item-template","name":"Custom Item Template","title":"Components/Select","importPath":"./src/components/Select/Select.stories.tsx","componentPath":"./src/components/Select/index.ts","tags":["dev","test"]},"components-sidebar--overview":{"id":"components-sidebar--overview","title":"Components/Sidebar","name":"Overview","importPath":"./src/components/Sidebar/Sidebar.stories.tsx","type":"docs","tags":["dev","test","autodocs"],"storiesImports":[]},"components-sidebar--sidebar":{"type":"story","id":"components-sidebar--sidebar","name":"Sidebar","title":"Components/Sidebar","importPath":"./src/components/Sidebar/Sidebar.stories.tsx","componentPath":"./src/components/Sidebar/index.ts","tags":["dev","test","autodocs"]},"components-sidebar--simply-sidebar":{"type":"story","id":"components-sidebar--simply-sidebar","name":"Simply Sidebar","title":"Components/Sidebar","importPath":"./src/components/Sidebar/Sidebar.stories.tsx","componentPath":"./src/components/Sidebar/index.ts","tags":["dev","test","autodocs"]},"components-sidebar--stepper":{"type":"story","id":"components-sidebar--stepper","name":"Stepper","title":"Components/Sidebar","importPath":"./src/components/Sidebar/Sidebar.stories.tsx","componentPath":"./src/components/Sidebar/index.ts","tags":["dev","test","autodocs"]},"components-spinner--overview":{"id":"components-spinner--overview","title":"Components/Spinner","name":"Overview","importPath":"./src/components/Spinner/Spinner.stories.tsx","type":"docs","tags":["dev","test","autodocs"],"storiesImports":[]},"components-spinner--primary":{"type":"story","id":"components-spinner--primary","name":"Primary","title":"Components/Spinner","importPath":"./src/components/Spinner/Spinner.stories.tsx","componentPath":"./src/components/Spinner/index.ts","tags":["dev","test","autodocs"]},"components-switch--overview":{"id":"components-switch--overview","title":"Components/Switch","name":"Overview","importPath":"./src/components/Switch/Switch.stories.tsx","type":"docs","tags":["dev","test"],"storiesImports":[]},"components-switch--normal-switch":{"type":"story","id":"components-switch--normal-switch","name":"Normal Switch","title":"Components/Switch","importPath":"./src/components/Switch/Switch.stories.tsx","componentPath":"./src/components/Switch/index.ts","tags":["dev","test"]},"components-switch--button-switch":{"type":"story","id":"components-switch--button-switch","name":"Button Switch","title":"Components/Switch","importPath":"./src/components/Switch/Switch.stories.tsx","componentPath":"./src/components/Switch/index.ts","tags":["dev","test","autodocs"]},"components-tab--overview":{"id":"components-tab--overview","title":"Components/Tab","name":"Overview","importPath":"./src/components/Tab/Tab.stories.tsx","type":"docs","tags":["dev","test","autodocs"],"storiesImports":[]},"components-tab--primary":{"type":"story","id":"components-tab--primary","name":"Primary","title":"Components/Tab","importPath":"./src/components/Tab/Tab.stories.tsx","componentPath":"./src/components/Tab/index.ts","tags":["dev","test","autodocs"]},"components-table--overview":{"id":"components-table--overview","title":"Components/Table","name":"Overview","importPath":"./src/components/Table/Table.stories.tsx","type":"docs","tags":["dev","test","autodocs"],"storiesImports":[]},"components-table--primary":{"type":"story","id":"components-table--primary","name":"Primary","title":"Components/Table","importPath":"./src/components/Table/Table.stories.tsx","componentPath":"./src/components/Table/index.ts","tags":["dev","test","autodocs"]},"components-toast--overview":{"id":"components-toast--overview","title":"Components/Toast","name":"Overview","importPath":"./src/components/Toast/Toast.stories.tsx","type":"docs","tags":["dev","test","autodocs"],"storiesImports":[]},"components-toast--primary":{"type":"story","id":"components-toast--primary","name":"Primary","title":"Components/Toast","importPath":"./src/components/Toast/Toast.stories.tsx","componentPath":"./src/components/Toast/index.ts","tags":["dev","test","autodocs"]},"components-tooltip--overview":{"id":"components-tooltip--overview","title":"Components/Tooltip","name":"Overview","importPath":"./src/components/Tooltip/Tooltip.stories.tsx","type":"docs","tags":["dev","test","autodocs"],"storiesImports":[]},"components-tooltip--primary":{"type":"story","id":"components-tooltip--primary","name":"Primary","title":"Components/Tooltip","importPath":"./src/components/Tooltip/Tooltip.stories.tsx","componentPath":"./src/components/Tooltip/index.ts","tags":["dev","test","autodocs"]},"components-typography--overview":{"id":"components-typography--overview","title":"Components/Typography","name":"Overview","importPath":"./src/components/Typography/Typography.stories.tsx","type":"docs","tags":["dev","test","autodocs"],"storiesImports":[]},"components-typography--display":{"type":"story","id":"components-typography--display","name":"Display","title":"Components/Typography","importPath":"./src/components/Typography/Typography.stories.tsx","componentPath":"./src/components/Typography/index.ts","tags":["dev","test","autodocs"]},"components-typography--headline":{"type":"story","id":"components-typography--headline","name":"Headline","title":"Components/Typography","importPath":"./src/components/Typography/Typography.stories.tsx","componentPath":"./src/components/Typography/index.ts","tags":["dev","test","autodocs"]},"components-typography--title":{"type":"story","id":"components-typography--title","name":"Title","title":"Components/Typography","importPath":"./src/components/Typography/Typography.stories.tsx","componentPath":"./src/components/Typography/index.ts","tags":["dev","test","autodocs"]},"components-typography--body":{"type":"story","id":"components-typography--body","name":"Body","title":"Components/Typography","importPath":"./src/components/Typography/Typography.stories.tsx","componentPath":"./src/components/Typography/index.ts","tags":["dev","test","autodocs"]},"components-typography--link":{"type":"story","id":"components-typography--link","name":"Link","title":"Components/Typography","importPath":"./src/components/Typography/Typography.stories.tsx","componentPath":"./src/components/Typography/index.ts","tags":["dev","test","autodocs"]},"components-typography--label":{"type":"story","id":"components-typography--label","name":"Label","title":"Components/Typography","importPath":"./src/components/Typography/Typography.stories.tsx","componentPath":"./src/components/Typography/index.ts","tags":["dev","test","autodocs"]},"components-upload--overview":{"id":"components-upload--overview","title":"Components/Upload","name":"Overview","importPath":"./src/components/Upload/Upload.stories.tsx","type":"docs","tags":["dev","test","autodocs"],"storiesImports":[]},"components-upload--primary":{"type":"story","id":"components-upload--primary","name":"Primary","title":"Components/Upload","importPath":"./src/components/Upload/Upload.stories.tsx","componentPath":"./src/components/Upload/index.ts","tags":["dev","test","autodocs"]},"components-upload--basic":{"type":"story","id":"components-upload--basic","name":"Basic","title":"Components/Upload","importPath":"./src/components/Upload/Upload.stories.tsx","componentPath":"./src/components/Upload/index.ts","tags":["dev","test","autodocs"]},"components-upload--file-bar":{"type":"story","id":"components-upload--file-bar","name":"File Bar","title":"Components/Upload","importPath":"./src/components/Upload/Upload.stories.tsx","componentPath":"./src/components/Upload/index.ts","tags":["dev","test","autodocs"]}}}